Workbook

Sheet retail_store_performance_dashbo
A1: Order_ID | B1: Order_Date | C1: Store_Name | D1: City | E1: State | F1: Region | G1: Store_Manager | H1: Category | I1: Product_Name | J1: Quantity | K1: Unit_Price | L1: Discount_Percent | M1: Discount_Amount | N1: Sales | O1: Cost | P1: Profit | Q1: Profit_Status | R1: Discount_Status | S1: Payment_Method | T1: Order_Status | U1: Customer_Rating | V1: Rating_Status
A2: ORD00003 | B2: 46023 | C2: Delhi Connaught | D2: Delhi | E2: Delhi | F2: North | G2: Amit Verma | H2: Electronics | I2: Smartwatch | J2: 3 | K2: 4642.54 | L2: 20 | M2: =J2*K2*L2/100 -> 2785.524 | N2: 11142.1 | O2: 8700 | P2: 2442.1 | Q2: =IF(retail_store_performance_dashbo!$P2>0,"Profit",IF(retail_store_performance_dashbo!$P2<0,"Loss","Break Even")) -> Profit | R2: {=_xlfn.IFS(L2=0,"No Discount",L2<=5,"Low Discount",L2<=10,"Medium Discount",L2<=20,"High Discount")} -> High Discount | S2: Cash | T2: Completed | U2: 4.8 | V2: {=_xlfn.IFS(U2=0,"Not Rated",U2>=4.5,"High Rating",U2>=3,"Medium Rating",U2<3,"Low Rating")} -> High Rating
A3: ORD00016 | B3: 46023 | C3: Hyderabad Banjara | D3: Hyderabad | E3: Telangana | F3: South | G3: Anjali Reddy | H3: Beauty | I3: Perfume | J3: 5 | K3: 1877.79 | L3: 0 | M3: =J3*K3*L3/100 -> 0 | N3: 9388.95 | O3: 5250 | P3: 4138.95 | Q3: =IF(retail_store_performance_dashbo!$P3>0,"Profit",IF(retail_store_performance_dashbo!$P3<0,"Loss","Break Even")) -> Profit | R3: {=_xlfn.IFS(L3=0,"No Discount",L3<=5,"Low Discount",L3<=10,"Medium Discount",L3<=20,"High Discount")} -> No Discount | S3: UPI | T3: Completed | U3: 3.4 | V3: {=_xlfn.IFS(U3=0,"Not Rated",U3>=4.5,"High Rating",U3>=3,"Medium Rating",U3<3,"Low Rating")} -> Medium Rating
A4: ORD00138 | B4: 46023 | C4: Bengaluru MG Road | D4: Bengaluru | E4: Karnataka | F4: South | G4: Vikram Rao | H4: Beauty | I4: Moisturizer | J4: 5 | K4: 541.07 | L4: 10 | M4: =J4*K4*L4/100 -> 270.535 | N4: 2434.82 | O4: 1700 | P4: 734.82 | Q4: =IF(retail_store_performance_dashbo!$P4>0,"Profit",IF(retail_store_performance_dashbo!$P4<0,"Loss","Break Even")) -> Profit | R4: {=_xlfn.IFS(L4=0,"No Discount",L4<=5,"Low Discount",L4<=10,"Medium Discount",L4<=20,"High Discount")} -> Medium Discount | S4: UPI | T4: Completed | U4: 4.9 | V4: {=_xlfn.IFS(U4=0,"Not Rated",U4>=4.5,"High Rating",U4>=3,"Medium Rating",U4<3,"Low Rating")} -> High Rating
A5: ORD00143 | B5: 46023 | C5: Bengaluru MG Road | D5: Bengaluru | E5: Karnataka | F5: South | G5: Vikram Rao | H5: Clothing | I5: Jacket | J5: 1 | K5: 3064.93 | L5: 5 | M5: =J5*K5*L5/100 -> 153.2465 | N5: 2911.68 | O5: 1900 | P5: 1011.68 | Q5: =IF(retail_store_performance_dashbo!$P5>0,"Profit",IF(retail_store_performance_dashbo!$P5<0,"Loss","Break Even")) -> Profit | R5: {=_xlfn.IFS(L5=0,"No Discount",L5<=5,"Low Discount",L5<=10,"Medium Discount",L5<=20,"High Discount")} -> Low Discount | S5: Net Banking | T5: Completed | U5: 3.7 | V5: {=_xlfn.IFS(U5=0,"Not Rated",U5>=4.5,"High Rating",U5>=3,"Medium Rating",U5<3,"Low Rating")} -> Medium Rating
A6: ORD00182 | B6: 46023 | C6: Jaipur Central | D6: Jaipur | E6: Rajasthan | F6: West | G6: Rajesh Sharma | H6: Grocery | I6: Cooking Oil 1L | J6: 2 | K6: 148.35 | L6: 20 | M6: =J6*K6*L6/100 -> 59.34 | N6: 0 | O6: 240 | P6: 0 | Q6: =IF(retail_store_performance_dashbo!$P6>0,"Profit",IF(retail_store_performance_dashbo!$P6<0,"Loss","Break Even")) -> Break Even | R6: {=_xlfn.IFS(L6=0,"No Discount",L6<=5,"Low Discount",L6<=10,"Medium Discount",L6<=20,"High Discount")} -> High Discount | S6: Cash | T6: Cancelled | U6: 0 | V6: {=_xlfn.IFS(U6=0,"Not Rated",U6>=4.5,"High Rating",U6>=3,"Medium Rating",U6<3,"Low Rating")} -> Not Rated
A7: ORD00206 | B7: 46023 | C7: Chennai T Nagar | D7: Chennai | E7: Tamil Nadu | F7: South | G7: Karthik Iyer | H7: Electronics | I7: Smartwatch | J7: 1 | K7: 4397.59 | L7: 5 | M7: =J7*K7*L7/100 -> 219.8795 | N7: 4177.71 | O7: 2900 | P7: 1277.71 | Q7: =IF(retail_store_performance_dashbo!$P7>0,"Profit",IF(retail_store_performance_dashbo!$P7<0,"Loss","Break Even")) -> Profit | R7: {=_xlfn.IFS(L7=0,"No Discount",L7<=5,"Low Discount",L7<=10,"Medium Discount",L7<=20,"High Discount")} -> Low Discount | S7: UPI | T7: Completed | U7: 3.5 | V7: {=_xlfn.IFS(U7=0,"Not Rated",U7>=4.5,"High Rating",U7>=3,"Medium Rating",U7<3,"Low Rating")} -> Medium Rating
A8: ORD00462 | B8: 46023 | C8: Bengaluru MG Road | D8: Bengaluru | E8: Karnataka | F8: South | G8: Vikram Rao | H8: Electronics | I8: Laptop | J8: 6 | K8: 57315.86 | L8: 15 | M8: =J8*K8*L8/100 -> 51584.274 | N8: 292310.89 | O8: 252000 | P8: 40310.89 | Q8: =IF(retail_store_performance_dashbo!$P8>0,"Profit",IF(retail_store_performance_dashbo!$P8<0,"Loss","Break Even")) -> Profit | R8: {=_xlfn.IFS(L8=0,"No Discount",L8<=5,"Low Discount",L8<=10,"Medium Discount",L8<=20,"High Discount")} -> High Discount | S8: Net Banking | T8: Completed | U8: 4.6 | V8: {=_xlfn.IFS(U8=0,"Not Rated",U8>=4.5,"High Rating",U8>=3,"Medium Rating",U8<3,"Low Rating")} -> High Rating
A9: ORD00181 | B9: 46024 | C9: Mumbai Andheri | D9: Mumbai | E9: Maharashtra | F9: West | G9: Neha Kapoor | H9: Electronics | I9: Smartphone | J9: 2 | K9: 22025.76 | L9: 0 | M9: =J9*K9*L9/100 -> 0 | N9: 44051.52 | O9: 32000 | P9: 12051.52 | Q9: =IF(retail_store_performance_dashbo!$P9>0,"Profit",IF(retail_store_performance_dashbo!$P9<0,"Loss","Break Even")) -> Profit | R9: {=_xlfn.IFS(L9=0,"No Discount",L9<=5,"Low Discount",L9<=10,"Medium Discount",L9<=20,"High Discount")} -> No Discount | S9: Credit Card | T9: Completed | U9: 3.6 | V9: {=_xlfn.IFS(U9=0,"Not Rated",U9>=4.5,"High Rating",U9>=3,"Medium Rating",U9<3,"Low Rating")} -> Medium Rating
A10: ORD00290 | B10: 46024 | C10: Chennai T Nagar | D10: Chennai | E10: Tamil Nadu | F10: South | G10: Karthik Iyer | H10: Home & Kitchen | I10: Water Bottle | J10: 5 | K10: 718.33 | L10: 0 | M10: =J10*K10*L10/100 -> 0 | N10: 3591.65 | O10: 2000 | P10: 1591.65 | Q10: =IF(retail_store_performance_dashbo!$P10>0,"Profit",IF(retail_store_performance_dashbo!$P10<0,"Loss","Break Even")) -> Profit | R10: {=_xlfn.IFS(L10=0,"No Discount",L10<=5,"Low Discount",L10<=10,"Medium Discount",L10<=20,"High Discount")} -> No Discount | S10: Net Banking | T10: Completed | U10: 4.5 | V10: {=_xlfn.IFS(U10=0,"Not Rated",U10>=4.5,"High Rating",U10>=3,"Medium Rating",U10<3,"Low Rating")} -> High Rating
A11: ORD00473 | B11: 46024 | C11: Lucknow Hazratganj | D11: Lucknow | E11: Uttar Pradesh | F11: North | G11: Sanjay Singh | H11: Clothing | I11: Sneakers | J11: 6 | K11: 4196.02 | L11: 20 | M11: =J11*K11*L11/100 -> 5035.224 | N11: 20140.9 | O11: 15600 | P11: 4540.9 | Q11: =IF(retail_store_performance_dashbo!$P11>0,"Profit",IF(retail_store_performance_dashbo!$P11<0,"Loss","Break Even")) -> Profit | R11: {=_xlfn.IFS(L11=0,"No Discount",L11<=5,"Low Discount",L11<=10,"Medium Discount",L11<=20,"High Discount")} -> High Discount | S11: Net Banking | T11: Completed | U11: 3.9 | V11: {=_xlfn.IFS(U11=0,"Not Rated",U11>=4.5,"High Rating",U11>=3,"Medium Rating",U11<3,"Low Rating")} -> Medium Rating
A12: ORD00133 | B12: 46025 | C12: Mumbai Andheri | D12: Mumbai | E12: Maharashtra | F12: West | G12: Neha Kapoor | H12: Beauty | I12: Moisturizer | J12: 5 | K12: 566.02 | L12: 10 | M12: =J12*K12*L12/100 -> 283.01 | N12: 2547.09 | O12: 1700 | P12: 847.09 | Q12: =IF(retail_store_performance_dashbo!$P12>0,"Profit",IF(retail_store_performance_dashbo!$P12<0,"Loss","Break Even")) -> Profit | R12: {=_xlfn.IFS(L12=0,"No Discount",L12<=5,"Low Discount",L12<=10,"Medium Discount",L12<=20,"High Discount")} -> Medium Discount | S12: UPI | T12: Completed | U12: 3.9 | V12: {=_xlfn.IFS(U12=0,"Not Rated",U12>=4.5,"High Rating",U12>=3,"Medium Rating",U12<3,"Low Rating")} -> Medium Rating
A13: ORD00159 | B13: 46025 | C13: Jaipur Central | D13: Jaipur | E13: Rajasthan | F13: West | G13: Rajesh Sharma | H13: Grocery | I13: Tea 500g | J13: 2 | K13: 266.78 | L13: 10 | M13: =J13*K13*L13/100 -> 53.356 | N13: 480.2 | O13: 420 | P13: 60.2 | Q13: =IF(retail_store_performance_dashbo!$P13>0,"Profit",IF(retail_store_performance_dashbo!$P13<0,"Loss","Break Even")) -> Profit | R13: {=_xlfn.IFS(L13=0,"No Discount",L13<=5,"Low Discount",L13<=10,"Medium Discount",L13<=20,"High Discount")} -> Medium Discount | S13: Net Banking | T13: Completed | U13: 4 | V13: {=_xlfn.IFS(U13=0,"Not Rated",U13>=4.5,"High Rating",U13>=3,"Medium Rating",U13<3,"Low Rating")} -> Medium Rating
... A501: ORD00476 | B501: 46262 | C501: Bengaluru MG Road | D501: Bengaluru | E501: Karnataka | F501: South | G501: Vikram Rao | H501: Clothing | I501: Jacket | J501: 4 | K501: 3121.79 | L501: 5 | M501: =J501*K501*L501/100 -> 624.358 | N501: -11862.8 | O501: 7600 | P501: -19462.8 | Q501: =IF(retail_store_performance_dashbo!$P501>0,"Profit",IF(retail_store_performance_dashbo!$P501<0,"Loss","Break Even")) -> Loss | R501: {=_xlfn.IFS(L501=0,"No Discount",L501<=5,"Low Discount",L501<=10,"Medium Discount",L501<=20,"High Discount")} -> Low Discount | S501: Net Banking | T501: Returned | U501: 3.1 | V501: {=_xlfn.IFS(U501=0,"Not Rated",U501>=4.5,"High Rating",U501>=3,"Medium Rating",U501<3,"Low Rating")} -> Medium Rating

Sheet Descriptive Summary
A1: Sales | D1: Profit
A3: Mean | B3: 14086.278 | D3: Mean | E3: 1626.1823
A4: Standard Error | B4: 2001.9184 | D4: Standard Error | E4: 562.45957
A5: Median | B5: 2520.63 | D5: Median | E5: 749.775
A6: Mode | B6: 0 | D6: Mode | E6: 0
A7: Standard Deviation | B7: 44764.255 | D7: Standard Deviation | E7: 12576.978
A8: Sample Variance | B8: 2.0038386e+09 | D8: Sample Variance | E8: 1.5818039e+08
A9: Kurtosis | B9: 24.545418 | D9: Kurtosis | E9: 111.97849
A10: Skewness | B10: 4.750143 | D10: Skewness | E10: -6.135683
A11: Range | B11: 432387.52 | D11: Range | E11: 260387.52
A12: Minimum | B12: -109213.9 | D12: Minimum | E12: -189213.9
A13: Maximum | B13: 323173.62 | D13: Maximum | E13: 71173.62
A14: Sum | B14: 7043139.1 | D14: Sum | E14: 813091.14
A15: Count | B15: 500 | D15: Count | E15: 500

Sheet Pivot Table
A1: Sales & Profit by Category | J1: Category Sales & Cost Analysis
A3: category | B3: Sum of Sales | C3: Sum of Profit | J3: Category | K3: Sum of Quantity | L3: Sum of Sales | M3: Sum of Cost
A4: Beauty | B4: 199315.58 | C4: 13945.58 | J4: Beauty | K4: 420 | L4: 199315.58 | M4: 194830
A5: Clothing | B5: 553022.52 | C5: 76772.52 | J5: Clothing | K5: 341 | L5: 553022.52 | M5: 511700
A6: Electronics | B6: 5537168.7 | C6: 676168.7 | J6: Electronics | K6: 326 | L6: 5537168.7 | M6: 4931900
A7: Grocery | B7: 77354.55 | C7: 7976.55 | J7: Grocery | K7: 311 | L7: 77354.55 | M7: 75828
A8: Home & Kitchen | B8: 676277.79 | C8: 38227.79 | J8: Home & Kitchen | K8: 348 | L8: 676277.79 | M8: 697250
A9: Grand Total | B9: 7043139.1 | C9: 813091.14 | J9: Grand Total | K9: 1746 | L9: 7043139.1 | M9: 6411508
E11: Store Performance
E13: Store Name | F13: Count of Order_ID | G13: Sum of Sales | H13: Sum of Profit
E14: Bengaluru MG Road | F14: 53 | G14: 621952.31 | H14: 38168.31
E15: Chennai T Nagar | F15: 61 | G15: 1133236.1 | H15: 241400.05
E16: Delhi Connaught | F16: 69 | G16: 634983.88 | H16: -79990.12
E17: Hyderabad Banjara | F17: 67 | G17: 1561295.4 | H17: 172259.43
E18: Jaipur Central | F18: 63 | G18: 975112.51 | H18: 96876.51
E19: Kolkata Park Street | F19: 59 | G19: 612455.14 | H19: 72635.14
E20: Lucknow Hazratganj | F20: 65 | G20: 421100.85 | H20: 39838.85
E21: Mumbai Andheri | F21: 63 | G21: 1083003 | H21: 231902.97
E22: Grand Total | F22: 500 | G22: 7043139.1 | H22: 813091.14 | J22: Payment Method Analysis
J24: Payment Method Analysis | K24: Count of Order_ID | L24: Sum of Sales | M24: Sum of Profit
A25: Order Status Analysis | J25: Cash | K25: 109 | L25: 1476305.9 | M25: 5619.94
J26: Credit Card | K26: 92 | L26: 990557.01 | M26: 172543.01
A27: Order status | B27: Count of Order_ID | C27: Sum of Sales | D27: Sum of Profit | J27: Debit Card | K27: 103 | L27: 1357226.2 | M27: 210594.17
A28: Cancelled | B28: 31 | C28: 0 | D28: 0 | J28: Net Banking | K28: 103 | L28: 2247149.8 | M28: 342097.83
A29: Completed | B29: 426 | C29: 7434291.8 | D29: 1480573.8 | J29: UPI | K29: 93 | L29: 971900.19 | M29: 82236.19
A30: Returned | B30: 43 | C30: -391152.61 | D30: -667482.61 | J30: Grand Total | K30: 500 | L30: 7043139.1 | M30: 813091.14
A31: Grand Total | B31: 500 | C31: 7043139.1 | D31: 813091.14
A34: Key Insight: 1.Sales & Profit by Category: Electronics recorded the highest Sales of ₹55,37,168.70 and the highest Profit of ₹6,76,168.70, while Grocery recorded the lowest Sales of ₹77,354.55 and the lowest Profit of ₹7,976.55. 2.Category Sales, Cost & Quantity Analysis: Beauty recorded the highest Quantity of 420 units, while Grocery recorded the lowest Quantity of 311 units. Electronics recorded the highest Sales of ₹55,37,168.70 and Cost of ₹49,31,900, while Grocery recorded the lowest Sales of ₹77,354.55 and Cost of ₹75,828. 3.Store Performance Analysis: Delhi Connaught recorded the highest number of orders with 69 Order IDs, while Bangalore MG Road recorded the lowest with 53 Order IDs. Hyderabad Banjara recorded the highest Sales of ₹15,61,295.43, while Lucknow Hazratganj recorded the lowest Sales of ₹4,21,100.85. Chennai T. Nagar recorded the highest Profit of ₹2,41,400.05, while Delhi Connaught recorded a Loss of ₹79,990.12. 4.Order Status Analysis: Completed orders accounted for 426 Order IDs, generating Sales of ₹74,34,291.75 and Profit of ₹14,80,573.75; Returns accounted for 43 Order IDs, resulting in negative Sales of ₹3,91,152.61 and a Loss of ₹6,67,482.61; Cancelled orders accounted for 31 Order IDs with zero Sales and zero Profit. 5.Payment Method Analysis: Cash recorded the highest number of orders with 109 Order IDs, while Credit Card recorded the lowest with 92 Order IDs. Net Banking generated the highest Sales of ₹22,47,149.83 and Profit of ₹3,42,097.83, while UPI recorded the lowest Sales of ₹9,71,900.90 and Cash recorded the lowest Profit of ₹5,619.94.
